setup.py
pyepvp/__init__.py
pyepvp/exceptions.py
pyepvp/icons.py
pyepvp/parser.py
pyepvp/privatemessages.py
pyepvp/regexp.py
pyepvp/session.py
pyepvp/shoutbox.py
pyepvp/tapatalk.py
pyepvp/tbm.py
pyepvp/threads.py
pyepvp.egg-info/PKG-INFO
pyepvp.egg-info/SOURCES.txt
pyepvp.egg-info/dependency_links.txt
pyepvp.egg-info/requires.txt
pyepvp.egg-info/top_level.txt
site/__init__.py