Metadata-Version: 1.1
Name: pyepvp
Version: 1.0.0
Summary: An python api for elitepvpers
Home-page: https://github.com/Der-Eddy/pyepvp
Author: Der-Eddy
Author-email: dereddyteddy@gmail.com
License: MIT
Keywords: api development
Platform: UNKNOWN
Classifier: Development Status :: 3 - Alpha
Classifier: Intended Audience :: Developers
Classifier: Topic :: Software Development :: Build Tools
Classifier: License :: OSI Approved :: MIT License
Classifier: Programming Language :: Python :: 3.4
Classifier: Programming Language :: Python :: 3.5
